boldi/__main__.py
boldi/_version.py
boldi-0.9.7.dist-info/METADATA
boldi-0.9.7.dist-info/WHEEL
boldi-0.9.7.dist-info/RECORD
