Metadata-Version: 2.4
Name: boldi
Version: 0.9.7
Summary: Boldi's Python libraries
Author-email: Boldizsár Palotás <boldizsar.palotas@gmail.com>
License: MIT
Requires-Python: >=3.10
Requires-Dist: boldi-cli==0.9.7
Requires-Dist: boldi-ctx==0.9.7
Requires-Dist: boldi-plugins==0.9.7
Provides-Extra: dev
Requires-Dist: boldi-dev; extra == 'dev'
